pmpc/__init__.py
pmpc/accelerated.py
pmpc/import_pmpcjl.py
pmpc/julia_utils.py
pmpc/problem_struct.py
pmpc/remote.py
pmpc/scp_mpc.py
pmpc/static_backend.py
pmpc/utils.py
pmpc/experimental/__init__.py
pmpc/experimental/dynamics_definitions.py
pmpc/experimental/jax_solver.py
pmpc/experimental/remote_like_interface.py
pmpc/experimental/second_order_solvers.py
pmpc/experimental/solver_definitions.py
pmpc/experimental/utils.py
pmpc/experimental/jax/__init__.py
pmpc/experimental/jax/dynamics.py
pmpc/experimental/jax/root.py
pmpc-0.7.1.dist-info/LICENSE
pmpc-0.7.1.dist-info/METADATA
pmpc-0.7.1.dist-info/WHEEL
pmpc-0.7.1.dist-info/top_level.txt
pmpc-0.7.1.dist-info/RECORD
