Metadata-Version: 2.1
Name: pmpc
Version: 0.7.1
Summary: Python-interface Particle Sequential Convex Programming Model Predictive Control (SCP PMPC) interface.
Author-email: Robert Dyro <rdyro@stanford.edu>
Project-URL: Homepage, https://github.com/StanfordASL/pmpc
Project-URL: Bug Tracker, https://github.com/StanfordASL/pmpc/issues
Classifier: Programming Language :: Python :: 3
Classifier: License :: OSI Approved :: MIT License
Classifier: Operating System :: OS Independent
Requires-Python: >=3.6
License-File: LICENSE
Requires-Dist: numpy
Requires-Dist: julia
Requires-Dist: zstandard
Requires-Dist: pyzmq
Requires-Dist: cloudpickle
Requires-Dist: redis
Requires-Dist: tqdm
Requires-Dist: psutil
